{"main.ts":"import { bootstrapApplication } from '@angular/platform-browser'; \n\nimport { appConfig } from './app/app.config'; \n\nimport { AppComponent } from './app.component';\n\nbootstrapApplication(AppComponent, appConfig).catch((err) => console.error(err));","angular.json":"{\n    \"$schema\": \"./node_modules/@angular/cli/lib/config/schema.json\",\n    \"version\": 1,\n    \"newProjectRoot\": \"projects\",\n    \"projects\": {\n      \"demo\": {\n        \"root\": \"\",\n        \"sourceRoot\": \"\",\n        \"projectType\": \"application\",\n        \"prefix\": \"app\",\n        \"schematics\": {},\n        \"architect\": {\n          \"build\": {\n            \"builder\": \"@angular-devkit/build-angular:browser\",\n            \"options\": {\n              \"outputPath\": \"dist/demo\",\n              \"index\": \"index.html\",\n              \"main\": \"main.ts\",\n              \"polyfills\": \"polyfills.ts\",\n              \"tsConfig\": \"tsconfig.app.json\",\n              \"assets\": [\n                \"favicon.ico\",\n                \"assets\"\n              ],\n              \"styles\": [\n                \n              ],\n              \"scripts\": []\n            },\n            \"configurations\": {\n              \"production\": {\n                \"fileReplacements\": [\n                  {\n                    \"replace\": \"src/environments/environment.ts\",\n                    \"with\": \"src/environments/environment.prod.ts\"\n                  }\n                ],\n                \"optimization\": true,\n                \"outputHashing\": \"all\",\n                \"sourceMap\": false,\n                \"extractCss\": true,\n                \"namedChunks\": false,\n                \"aot\": true,\n                \"extractLicenses\": true,\n                \"vendorChunk\": false,\n                \"buildOptimizer\": true\n              }\n            }\n          },\n          \"serve\": {\n            \"builder\": \"@angular-devkit/build-angular:dev-server\",\n            \"options\": {\n              \"browserTarget\": \"demo:build\"\n            },\n            \"configurations\": {\n              \"production\": {\n                \"browserTarget\": \"demo:build:production\"\n              }\n            }\n          },\n          \"extract-i18n\": {\n            \"builder\": \"@angular-devkit/build-angular:extract-i18n\",\n            \"options\": {\n              \"browserTarget\": \"demo:build\"\n            }\n          },\n          \"test\": {\n            \"builder\": \"@angular-devkit/build-angular:karma\",\n            \"options\": {\n              \"main\": \"src/test.ts\",\n              \"polyfills\": \"src/polyfills.ts\",\n              \"tsConfig\": \"src/tsconfig.spec.json\",\n              \"karmaConfig\": \"src/karma.conf.js\",\n              \"styles\": [\n                \"styles.css\"\n              ],\n              \"scripts\": [],\n              \"assets\": [\n                \"src/favicon.ico\",\n                \"src/assets\"\n              ]\n            }\n          },\n          \"lint\": {\n            \"builder\": \"@angular-devkit/build-angular:tslint\",\n            \"options\": {\n              \"tsConfig\": [\n                \"src/tsconfig.app.json\",\n                \"src/tsconfig.spec.json\"\n              ],\n              \"exclude\": [\n                \"**/node_modules/**\"\n              ]\n            }\n          }\n        }\n      }\n    },\n    \"defaultProject\": \"demo\"\n  }\n  \n","app.component.ts":"import { Component, ViewEncapsulation, ViewChild, OnInit } from '@angular/core';\nimport {\n    DiagramComponent, DiagramModule, SnapSettingsModel, NodeModel, ConnectorModel, ShapeAnnotationModel, SnapConstraints,\n    DiagramTools, PointPortModel, ShapeStyleModel, PortVisibility, PointModel,\n    HorizontalAlignment, VerticalAlignment, TextAlign\n} from '@syncfusion/ej2-angular-diagrams';\n\n\n\n/**\n * Sample for Venn Diagram\n */\n\n@Component({\n    selector: 'app-root',\n    templateUrl: 'app.component.html',\n    styleUrls: ['app.component.css'],\n    encapsulation: ViewEncapsulation.None,\n    standalone: true,\n    imports: [ DiagramModule, ]\n})\nexport class AppComponent {\n    @ViewChild('diagram')\n    public diagram!: DiagramComponent;\n\n    // --- Diagram Settings ---\n    public tool: DiagramTools = DiagramTools.ZoomPan;\n    public snapSettings: SnapSettingsModel = { constraints: SnapConstraints.None };\n    public nodes!: NodeModel[];\n    public connectors!: ConnectorModel[];\n\n    ngOnInit(): void {\n        this.initializeDiagram();\n    }\n\n    private initializeDiagram() {\n        //Annotation Content\n        const trigonometryContent = 'Trigonometry is a branch \\nof mathematics that studies \\nthe relationship between \\nthe sides and angles of triangles.';\n        const assemblyContent = 'An assembly is a collection \\n of types and resources \\nbuilt to work together as \\na logical and functional unit.';\n        const middlewareContent = 'Software that acts as \\na bridge between an operating system\\n or database and applications,\\n especially over a network.';\n        const thesisContent = 'A statement or theory\\n put forward as a premise \\nto be maintained or proved.';\n        const expertiseContent = 'Expert skill or knowledge \\nin a particular field.';\n        const programmingContent = 'Programming is the process \\nof writing code that tells \\na computer application or \\nsoftware program what to do.';\n\n        // Path Shapes\n        const assemblyPath = 'M24.3267 27.4281H1.99727C0.894207 27.4281 0 26.551 0 25.469V2.93873C0 1.31571 1.34131 0 2.9959 0H8.10891C8.78495 0.0022957 9.44005 0.230314 9.96637 0.646519L13.9609 3.70279C14.1374 3.83974 14.3551 3.91551 14.5801 3.9183H23.0485C24.7031 3.9183 26.0444 5.23401 26.0444 6.85703V9.79575H29.0003C30.0366 9.80121 30.9975 10.3282 31.5449 11.1913C32.0923 12.0545 32.1496 13.1328 31.6966 14.0471L26.1642 26.331C25.8219 27.0166 25.1048 27.4448 24.3267 27.4281ZM2.61621 25.469H24.3265L29.819 13.2243C30.0052 12.9162 30.0052 12.5331 29.819 12.2251C29.6396 11.9284 29.3118 11.7489 28.9602 11.7549H10.2458C9.86524 11.7587 9.51861 11.9703 9.347 12.3035L2.61621 25.469ZM2.99668 1.95911C2.44515 1.95911 1.99805 2.39768 1.99805 2.93868V22.4126L7.55045 11.5198C8.05333 10.5213 9.0915 9.89056 10.2268 9.89366H23.988V6.95494C23.9773 6.41831 23.5364 5.98579 22.9893 5.97536H14.5209C13.8475 5.97709 13.1932 5.75624 12.6635 5.34844L8.66892 2.27257C8.49247 2.13563 8.27475 2.05985 8.04977 2.05706L2.99668 1.95911Z';\n        const middlewarePath = 'M28 12.56V32H8V26H0V0H13.44L19.44 6H21.44L28 12.56ZM8 6H16.58L12.58 2H2V24H8V6ZM26.001 14H20.001V8H10.001V30H26.001V14ZM21.999 12H24.579L21.999 9.41998V12Z';\n        const thesisPath = 'M22.7097 24.7742L24.7742 22.7097V28.9032H0V8.25806H2.06452V26.8387H22.7097V24.7742ZM20.6452 16.5161C19.2688 16.5161 17.9194 16.6559 16.5968 16.9355C15.2849 17.2043 14.0161 17.6075 12.7903 18.1452C11.5645 18.672 10.3925 19.3226 9.27419 20.0968C8.16667 20.8602 7.13978 21.7312 6.19355 22.7097V20.6452C6.19355 19.3118 6.36559 18.0323 6.70968 16.8065C7.05376 15.5699 7.53763 14.4194 8.16129 13.3548C8.7957 12.2796 9.54839 11.3065 10.4194 10.4355C11.3011 9.55376 12.2742 8.80107 13.3387 8.17742C14.414 7.54301 15.5645 7.05376 16.7903 6.70968C18.0269 6.36559 19.3118 6.19355 20.6452 6.19355V0L32 11.3548L20.6452 22.7097V16.5161ZM22.7097 8.25806C22.0538 8.25806 21.4409 8.26344 20.871 8.27419C20.3011 8.27419 19.7419 8.30107 19.1935 8.35484C18.6559 8.4086 18.1129 8.50538 17.5645 8.64516C17.0161 8.77419 16.4355 8.96774 15.8226 9.22581C14.8871 9.6129 14.0161 10.1075 13.2097 10.7097C12.414 11.3118 11.6989 12 11.0645 12.7742C10.4409 13.5376 9.9086 14.371 9.46774 15.2742C9.03763 16.1667 8.72043 17.1075 8.51613 18.0968C10.3226 16.8925 12.2527 15.9839 14.3065 15.371C16.3602 14.7581 18.4731 14.4516 20.6452 14.4516H22.7097V17.7258L29.0806 11.3548L22.7097 4.98387V8.25806Z';\n        const calendarPath = 'M9.0833333,10.083334 L11,10.083334 11,12 9.0833333,12 z M1,5 L1,14 13,14 13,5 z M1,2 L1,4 13,4 13,2 12,2 12,2.5 C12,2.776 11.776,3 11.5,3 11.224,3 11,2.776 11,2.5 L11,2 3,2 3,2.5 C3,2.776 2.776,3 2.5,3 2.224,3 2,2.776 2,2.5 L2,2 z M2.5,0 C2.776,0 3,0.22399998 3,0.5 L3,1 11,1 11,0.5 C11,0.22399998 11.224,0 11.5,0 11.776,0 12,0.22399998 12,0.5 L12,1 14,1 14,4 14,5 14,15 0,15 0,5 0,4 0,1 2,1 2,0.5 C2,0.22399998 2.224,0 2.5,0 z';\n        const notesPath = 'M11,4.7110004 L11,6 12.289001,6 z M5,4 L5,15 13,15 13,7 10,7 10,4 z M1,1 L1,12 4,12 4,3 8.2890015,3 6.2890015,1 z M0,0 L6.7109985,0 9.7109985,3 10.710999,3 14,6.2890015 14,16 4,16 4,13 0,13 z';\n        const pastePath = 'M24 32H0V3.99981H8C8.01001 3.469 8.12559 2.94549 8.34 2.4598C8.55076 1.99273 8.84184 1.56626 9.2 1.19979C9.56763 0.828696 10.0019 0.530157 10.48 0.319788C11.4554 -0.106596 12.5646 -0.106596 13.54 0.319788C14.4839 0.757643 15.2421 1.51586 15.68 2.4598C15.8875 2.9469 15.9963 3.47036 16 3.99981H24V32ZM22 11.9999V5.99983H20V9.99985H4V5.99983H2V30H22M6 5.99988V7.99989H18V5.99988H14V4.25987C13.9895 3.96985 13.9493 3.68167 13.88 3.39986C13.816 3.13337 13.7005 2.88198 13.54 2.65986C13.3845 2.4358 13.1791 2.25094 12.94 2.11986C12.6391 2.01205 12.3183 1.9711 12 1.99986C11.5422 1.94796 11.084 2.09343 10.74 2.39986C10.4674 2.68388 10.2623 3.02569 10.14 3.39986C10.0201 3.829 9.97282 4.27514 10 4.71987V5.99988H6Z';\n\n        // --- Create Ports ---\n        const programmingPort1: PointPortModel = this.createPort('port1', 0.82, 0.35);\n        const programmingPort2: PointPortModel = this.createPort('port2', 0.50, 0.8);\n        const thesisPort: PointPortModel = this.createPort('port1', -0.5, 0.5);\n        const middlewarePort: PointPortModel = this.createPort('port1', 1.5, 0.5);\n        const assemblyPort: PointPortModel = this.createPort('port1', -0.5, 0.5);\n        const trigonometryPort: PointPortModel = this.createPort('port1', 0.50, 0.8);\n\n        // --- Create Annotations ---\n        const trigonometryAnnotation: ShapeAnnotationModel[] = this.createAnnotations('Trigonometry', trigonometryContent, { x: 0.86, y: 0.30 }, { x: 0.46, y: 0.44 }, 'Right', undefined, 'Left');\n        const assemblyAnnotation: ShapeAnnotationModel[] = this.createAnnotations('Assembly', assemblyContent, { x: 1.3, y: 0.2 }, { x: 1.3, y: 1.9 }, 'Left', undefined, 'Left', undefined, 'Left', 240, 150);\n        const middlewareAnnotation: ShapeAnnotationModel[] = this.createAnnotations('Middleware', middlewareContent, { x: -0.4, y: 0.1 }, { x: -0.3, y: 1.7 }, 'Right', undefined, 'Right', undefined, 'Right', 240, 150);\n        const thesisAnnotation: ShapeAnnotationModel[] = this.createAnnotations('Thesis', thesisContent, { x: 1.3, y: 0.2 }, { x: 1.3, y: 2 }, 'Left', undefined, 'Left', undefined, 'Left', 240, 150);\n        const expertiseAnnotation: ShapeAnnotationModel[] = this.createAnnotations('Expertise', expertiseContent, { x: 0.5, y: 0.7 }, { x: 0.5, y: 0.80 });\n        const programmingAnnotation: ShapeAnnotationModel[] = this.createAnnotations('Programming', programmingContent, { x: 0.24, y: 0.3 }, { x: 0.18, y: 0.44 }, 'Left', undefined, 'Left', undefined);\n        programmingAnnotation.push({\n            content: 'Data\\n Science',\n            offset: { x: 0.91, y: 0.7 },\n            horizontalAlignment: 'Right',\n            style: { bold: true, fontFamily: 'Roboto', fontSize: 16 }\n        });\n\n        // --- Create Nodes ---\n        this.nodes = [\n            this.createNode('trigonometry', 615, 255, 350, 350, '#4582F966', '#4582F966', 'Basic', undefined, trigonometryAnnotation, [trigonometryPort]),\n            this.createNode('expertise', 500, 465, 350, 350, '#E86F6D66', '#E86F6D66', 'Basic', undefined, expertiseAnnotation),\n            this.createNode('programming', 390, 255, 350, 350, '#2DC28666', '#2DC28666', 'Basic', undefined, programmingAnnotation, [programmingPort1, programmingPort2]),\n            this.createNode('assemblyNode', 760, 35, 32, 28, '#1D747A', '#1D747A', 'Path', assemblyPath, assemblyAnnotation, [assemblyPort]),\n            this.createNode('middlewareNode', 250, 500, 28, 32, '#1E7649', '#1E7649', 'Path', middlewarePath, middlewareAnnotation, [middlewarePort]),\n            this.createNode('thesisNode', 800, 500, 32, 28, '#3A2C7D', '#3A2C7D', 'Path', thesisPath, thesisAnnotation, [thesisPort]),\n            this.createNode('calendarNode', 495, 500, 32, 32, '#952B2A', '#952B2A', 'Path', calendarPath),\n            this.createNode('notesNode', 338, 150, 22, 28, '#187851', '#187851', 'Path', notesPath),\n            this.createNode('pasteNode', 690, 150, 24, 32, '#213895', '#213895', 'Path', pastePath)\n        ];\n\n        // --- Create Connectors ---\n        const middlewareToProgramming: ConnectorModel = this.createConnector('middlewareToProgramming', '', 'middlewareNode', 'programming', '#494949', 1, 'port1', 'port2');\n        const assemblyToProgramming: ConnectorModel = this.createConnector('assemblyToProgramming', '', 'assemblyNode', 'programming', '#494949', 1, 'port1', 'port1');\n        assemblyToProgramming.segments = [{\n                type: 'Bezier',\n                vector1: { angle: 190, distance: 100 },\n                vector2: { angle: 280, distance: 100 }\n            }];\n        const thesisToTrigonometry: ConnectorModel = this.createConnector('thesisToTrigonometry', '', 'thesisNode', 'trigonometry', '#494949', 1, 'port1', 'port1');\n\n        this.connectors = [middlewareToProgramming, assemblyToProgramming, thesisToTrigonometry];\n    }\n\n    /**\n     * Creates a ConnectorModel object for the diagram.\n     * @param id The unique identifier for the connector.\n     * @param lineDashArray The dash array for the connector's stroke.\n     * @param source The ID of the source node.\n     * @param target The ID of the target node.\n     * @param lineColor The color of the connector's stroke.\n     * @param lineWidth The width of the connector's stroke.\n     * @param sourcePortId The ID of the source port.\n     * @param targetPortId The ID of the target port.\n     * @returns A ConnectorModel object configured with the provided properties.\n     */\n    private createConnector(id: string, lineDashArray: string, source: string, target: string,\n        lineColor: string, lineWidth: number, sourcePortId: string, targetPortId: string): ConnectorModel {\n        const connector: ConnectorModel = {\n            id: id,\n            sourceID: source,\n            targetID: target,\n            type: 'Bezier',\n            bezierSettings: { allowSegmentsReset: false },\n            style: {\n                strokeColor: lineColor,\n                strokeWidth: lineWidth,\n                strokeDashArray: lineDashArray\n            },\n            targetDecorator: {\n                shape: 'Circle',\n                width: 6,\n                height: 6,\n                style: {\n                    strokeColor: '#1D747A',\n                    fill: '#1D747A'\n                }\n            },\n            sourceDecorator: {\n                shape: 'Circle',\n                width: 6,\n                height: 6,\n                style: {\n                    strokeColor: '#1D747A',\n                    fill: '#1D747A'\n                }\n            },\n            sourcePortID: sourcePortId,\n            targetPortID: targetPortId\n        };\n        return connector;\n    }\n\n    /**\n     * Creates a node object for the Syncfusion EJ2 Diagram.\n     * @param id The unique identifier for the node.\n     * @param offsetX The x-coordinate of the node's position.\n     * @param offsetY The y-coordinate of the node's position.\n     * @param width The width of the node.\n     * @param height The height of the node.\n     * @param fill The background color of the node.\n     * @param strokeColor The border color of the node.\n     * @param shape The shape type of the node ('Basic' or 'Path').\n     * @param pathData The data for the path shape (if applicable).\n     * @param annotations An array of annotation objects for the node.\n     * @param ports An array of port objects for the node.\n     * @returns A NodeModel object configured with the provided properties.\n     */\n    private createNode(id: string, offsetX: number, offsetY: number, width: number, height: number,\n        fill: string, strokeColor: string, shape: 'Basic' | 'Path', pathData?: string,\n        annotations?: ShapeAnnotationModel[], ports?: PointPortModel[]): NodeModel {\n        const style: ShapeStyleModel = {\n            fill: fill,\n            strokeColor: strokeColor\n        };\n\n        const node: NodeModel = {\n            id: id,\n            offsetX: offsetX,\n            offsetY: offsetY,\n            width: width,\n            height: height,\n            annotations: annotations,\n            ports: ports,\n            style: style\n        };\n\n        if (shape === 'Basic') {\n            node.shape = {\n                type: 'Basic',\n                shape: 'Ellipse'\n            };\n        }\n        else {\n            node.shape = {\n                type: 'Path',\n                data: pathData\n            };\n            node.style!.strokeWidth = 0;\n        }\n        return node;\n    }\n\n    /**\n     * Creates an array of ShapeAnnotationModel objects for a diagram node.\n     * @param content1 The content for the first primary annotation.\n     * @param content2 The content for the second annotation.\n     * @param offset1 The offset for the first annotation.\n     * @param offset2 The offset for the second annotation.\n     * @param hAlign1 Horizontal alignment for the first annotation.\n     * @param vAlign1 Vertical alignment for the first annotation.\n     * @param hAlign2 Horizontal alignment for the second annotation.\n     * @param vAlign2 Vertical alignment for the second annotation.\n     * @param textAlign Text alignment for the second annotation's style.\n     * @param width The width for the second annotation.\n     * @param height The height for the second annotation.\n     * @returns An array of ShapeAnnotationModel objects.\n     */\n    private createAnnotations(content1: string, content2: string, offset1: PointModel, offset2: PointModel,\n        hAlign1?: HorizontalAlignment, vAlign1?: VerticalAlignment, hAlign2?: HorizontalAlignment, vAlign2?: VerticalAlignment,\n        textAlign: TextAlign = 'Center', width: number = 0, height: number = 0): ShapeAnnotationModel[] {\n\n        const annotations: ShapeAnnotationModel[] = [\n            // First annotation\n            {\n                content: content1,\n                offset: offset1,\n                style: {\n                    bold: true,\n                    fontFamily: 'Roboto',\n                    fontSize: 16\n                }\n            },\n            // Second annotation\n            {\n                content: content2,\n                offset: offset2,\n                style: {\n                    fontFamily: 'Roboto',\n                    fontSize: 12\n                }\n            }\n        ];\n\n        if (width > 0 && annotations[1]) {\n            annotations[1].width = width;\n            annotations[1].height = height;\n        }\n\n        if (hAlign1 && annotations[0]) {\n            annotations[0].horizontalAlignment = hAlign1;\n        }\n        if (hAlign2 && annotations[1]) {\n            annotations[1].horizontalAlignment = hAlign2;\n        }\n\n        if (vAlign1 && annotations[0]) {\n            annotations[0].verticalAlignment = vAlign1;\n        }\n        if (vAlign2 && annotations[1]) {\n            annotations[1].verticalAlignment = vAlign2;\n        }\n\n        if (textAlign !== 'Center' && annotations[1]?.style) {\n            (annotations[1].style).textAlign = textAlign;\n        }\n        return annotations;\n    }\n\n    /**\n     * Creates a PointPortModel object for a diagram node.\n     * @param id The unique identifier for the port.\n     * @param x The x-coordinate of the port's offset relative to the node.\n     * @param y The y-coordinate of the port's offset relative to the node.\n     * @returns A PointPortModel object configured with the provided properties.\n     */\n    private createPort(id: string, x: number, y: number): PointPortModel {\n        return {\n            id: id,\n            offset: { x: x, y: y },\n            visibility: PortVisibility.Hidden\n        };\n    }\n    \n    private diagramCreated: boolean = false;\n    public created(): void {\n        this.diagramCreated = true;\n        this.diagram.fitToPage();\n    }\n    public load(): void {\n        if (this.diagramCreated) {\n            this.diagram.fitToPage();\n        }\n    }\n}","polyfills.ts":"import 'zone.js';","app/app.config.ts":"import { ApplicationConfig } from '@angular/core';\n\n export const appConfig: ApplicationConfig = { providers: [], };","index.html":"<!doctype html>\n        <html lang=\"en\">\n          <head>\n            <meta charset=\"utf-8\">\n            <title>Window</title>\n            <base href=\"/\">\n            <meta name=\"viewport\" content=\"width=device-width, initial-scale=1\">\n            <link rel=\"icon\" type=\"image/x-icon\" href=\"favicon.ico\">\n            <link href=\"https://maxcdn.bootstrapcdn.com/bootstrap/3.3.7/css/bootstrap.min.css\" rel=\"stylesheet\" >\n          </head>\n          <body class=\"ej2-new\"> \n\n              <!-- Google Tag Manager (noscript) -->\n              <noscript><iframe src=\"https://www.googletagmanager.com/ns.html?id=GTM-P3WXFWCW\" height=\"0\" width=\"0\" style=\"display:none;visibility:hidden\"></iframe></noscript>\n              <noscript><iframe src=\"https://www.googletagmanager.com/ns.html?id=GTM-W8WD8WN\" height=\"0\" width=\"0\" style=\"display:none;visibility:hidden\"></iframe></noscript>\n              <!-- End Google Tag Manager (noscript) -->\n           <div hidden id=\"sync-analytics\" data-queue=\"EJ2 - Angular - Demos\"></div>\n            <app-root></app-root>\n          </body>\n        </html>","app.component.html":"<style>\r\n.control-section{\r\n    margin-top: 100px;\r\n}\r\n\r</style>\n\n<div class=\"control-section\">\n    <ejs-diagram #diagram id=\"diagram\" width=\"100%\" height=\"700px\" [tool]=\"tool\" [snapSettings]=\"snapSettings\"\n        [nodes]=\"nodes\" [connectors]=\"connectors\" (created)=\"created()\" (load)=\"load()\">\n    </ejs-diagram>\n</div>\n","app.component.css":".control-fluid {\n    padding: 0px !important;\n}","dependencies.json":"{\"@syncfusion/ej2-angular-base\":\"*\",\"@syncfusion/ej2-base\":\"*\",\"@syncfusion/ej2-diagrams\":\"*\",\"tslib\":\"^2.3.0\",\"@syncfusion/ej2-angular-diagrams\":\"*\",\"@syncfusion/ej2-buttons\":\"*\",\"@syncfusion/ej2-angular-buttons\":\"*\",\"@syncfusion/ej2-splitbuttons\":\"*\",\"@syncfusion/ej2-angular-splitbuttons\":\"*\",\"@syncfusion/ej2-inputs\":\"*\",\"@syncfusion/ej2-angular-inputs\":\"*\",\"@syncfusion/ej2-navigations\":\"*\",\"@syncfusion/ej2-angular-navigations\":\"*\",\"@syncfusion/ej2-dropdowns\":\"*\",\"@syncfusion/ej2-angular-dropdowns\":\"*\",\"@syncfusion/ej2-circulargauge\":\"*\",\"@syncfusion/ej2-angular-circulargauge\":\"*\",\"@syncfusion/ej2-calendars\":\"*\",\"@syncfusion/ej2-angular-calendars\":\"*\",\"@syncfusion/ej2-lists\":\"*\",\"@syncfusion/ej2-angular-lists\":\"*\",\"@syncfusion/ej2-grids\":\"*\",\"@syncfusion/ej2-angular-grids\":\"*\",\"@syncfusion/ej2-charts\":\"*\",\"@syncfusion/ej2-angular-charts\":\"*\",\"@syncfusion/ej2-popups\":\"*\",\"@syncfusion/ej2-angular-popups\":\"*\",\"@syncfusion/ej2-data\":\"*\",\"codemirror\":\"5.65.15\",\"marked\":\"0.3.19\",\"@types/codemirror\":\"0.0.56\",\"@types/marked\":\"0.3.0\",\"@angular/http\":\"*\",\"rxjs-compat\":\"*\",\"core-js\":\"2.6.9\",\"fuse.js\":\"^7.0.0\"}"}