{"main.ts":"import { bootstrapApplication } from '@angular/platform-browser'; \n\nimport { appConfig } from './app/app.config'; \n\nimport { AppComponent } from './app.component';\n\nbootstrapApplication(AppComponent, appConfig).catch((err) => console.error(err));","angular.json":"{\n    \"$schema\": \"./node_modules/@angular/cli/lib/config/schema.json\",\n    \"version\": 1,\n    \"newProjectRoot\": \"projects\",\n    \"projects\": {\n      \"demo\": {\n        \"root\": \"\",\n        \"sourceRoot\": \"\",\n        \"projectType\": \"application\",\n        \"prefix\": \"app\",\n        \"schematics\": {},\n        \"architect\": {\n          \"build\": {\n            \"builder\": \"@angular-devkit/build-angular:browser\",\n            \"options\": {\n              \"outputPath\": \"dist/demo\",\n              \"index\": \"index.html\",\n              \"main\": \"main.ts\",\n              \"polyfills\": \"polyfills.ts\",\n              \"tsConfig\": \"tsconfig.app.json\",\n              \"assets\": [\n                \"favicon.ico\",\n                \"assets\"\n              ],\n              \"styles\": [\n                \n              ],\n              \"scripts\": []\n            },\n            \"configurations\": {\n              \"production\": {\n                \"fileReplacements\": [\n                  {\n                    \"replace\": \"src/environments/environment.ts\",\n                    \"with\": \"src/environments/environment.prod.ts\"\n                  }\n                ],\n                \"optimization\": true,\n                \"outputHashing\": \"all\",\n                \"sourceMap\": false,\n                \"extractCss\": true,\n                \"namedChunks\": false,\n                \"aot\": true,\n                \"extractLicenses\": true,\n                \"vendorChunk\": false,\n                \"buildOptimizer\": true\n              }\n            }\n          },\n          \"serve\": {\n            \"builder\": \"@angular-devkit/build-angular:dev-server\",\n            \"options\": {\n              \"browserTarget\": \"demo:build\"\n            },\n            \"configurations\": {\n              \"production\": {\n                \"browserTarget\": \"demo:build:production\"\n              }\n            }\n          },\n          \"extract-i18n\": {\n            \"builder\": \"@angular-devkit/build-angular:extract-i18n\",\n            \"options\": {\n              \"browserTarget\": \"demo:build\"\n            }\n          },\n          \"test\": {\n            \"builder\": \"@angular-devkit/build-angular:karma\",\n            \"options\": {\n              \"main\": \"src/test.ts\",\n              \"polyfills\": \"src/polyfills.ts\",\n              \"tsConfig\": \"src/tsconfig.spec.json\",\n              \"karmaConfig\": \"src/karma.conf.js\",\n              \"styles\": [\n                \"styles.css\"\n              ],\n              \"scripts\": [],\n              \"assets\": [\n                \"src/favicon.ico\",\n                \"src/assets\"\n              ]\n            }\n          },\n          \"lint\": {\n            \"builder\": \"@angular-devkit/build-angular:tslint\",\n            \"options\": {\n              \"tsConfig\": [\n                \"src/tsconfig.app.json\",\n                \"src/tsconfig.spec.json\"\n              ],\n              \"exclude\": [\n                \"**/node_modules/**\"\n              ]\n            }\n          }\n        }\n      }\n    },\n    \"defaultProject\": \"demo\"\n  }\n  \n","app.component.ts":"import { Component, ViewEncapsulation } from '@angular/core';\nimport { HeatMap, Legend, Adaptor, Tooltip, ILoadedEventArgs, ITooltipEventArgs, HeatMapTheme, HeatMapModule } from '@syncfusion/ej2-angular-heatmap';\nHeatMap.Inject(Tooltip, Legend, Adaptor);\n\n@Component({\n    selector: 'app-root',\n    templateUrl: 'app.component.html',\n    encapsulation: ViewEncapsulation.None,\n    standalone: true,\n    imports: [HeatMapModule]\n})\nexport class AppComponent {\n\n    titleSettings: Object = {\n        text: 'Olympic Medal Achievements of most Successful Countries',\n        textStyle: {\n            size: '15px',\n            fontWeight: '500',\n            fontStyle: 'Normal',\n            fontFamily: 'inherit'\n        }\n    };\n    xAxis: Object = {\n        labels: ['China', 'France', 'GBR', 'Germany', 'Italy', 'Japan', 'KOR', 'Russia', 'USA'],\n        labelRotation: 45,\n        labelIntersectAction: 'None',\n        textStyle: {\n            fontFamily: 'inherit'\n        }\n    };\n    yAxis: Object = {\n        title: { \n            text: 'Olympic Year',\n            textStyle: {\n                size: '15px',\n                fontWeight: '500',\n                fontStyle: 'Normal',\n                fontFamily: 'inherit'\n            }\n        },\n        labels: ['2000', '2004', '2008', '2012', '2016'],\n        textStyle: {\n            fontFamily: 'inherit'\n        }\n    };\n    dataSource: Object = [\n            { 'Region': 'USA', '2000': 93, '2004': 101, '2008': 112, '2012': 103, '2016': 121 },\n            { 'Region': 'GBR', '2000': 28, '2004': 30, '2008': 49, '2012': 65, '2016': 67 },\n            { 'Region': 'China', '2000': 58, '2004': 63, '2008': 100, '2012': 91, '2016': 70 },\n            { 'Region': 'Russia', '2000': 89, '2004': 90, '2008': 60, '2012': 69, '2016': 55 },\n            { 'Region': 'Germany', '2000': 56, '2004': 49, '2008': 41, '2012': 44, '2016': 42 },\n            { 'Region': 'Japan', '2000': 18, '2004': 37, '2008': 25, '2012': 38, '2016': 41 },\n            { 'Region': 'France', '2000': 38, '2004': 33, '2008': 43, '2012': 35, '2016': 42 },\n            { 'Region': 'KOR', '2000': 28, '2004': 30, '2008': 32, '2012': 30, '2016': 21 },\n            { 'Region': 'Italy', '2000': 34, '2004': 32, '2008': 27, '2012': 28, '2016': 28 }];\n    dataSourceSettings: Object = {\n        isJsonData: true,\n        adaptorType: 'Table',\n        xDataMapping: 'Region',\n    };\n    public paletteSettings: Object = {\n        palette: [{ color: '#F0C27B' },\n        { color: '#4B1248' }\n        ],\n    };\n    public cellSettings: Object = {\n        border: {\n            width: 1,\n            radius: 4,\n            color: 'white'\n        },\n        textStyle: {\n            fontFamily: 'inherit'\n        }\n    };\n    public legendSettings: Object = {\n        textStyle: {\n             fontFamily: 'inherit'\n         }\n     };\n     public tooltipSettings: Object = {\n        textStyle: {\n            fontFamily: 'inherit'\n        }\n    };\n    public tooltipRender(args: ITooltipEventArgs): void {\n        args.content = [args.yLabel + ' | ' + args.xLabel + ' : ' + args.value + ' Medals'];\n    };\n    public load(args: ILoadedEventArgs): void {\n        // custom code start\n        let selectedTheme: string = location.hash.split('/')[1];\n        selectedTheme = selectedTheme ? selectedTheme : 'Material';\n        args.heatmap.theme = <HeatMapTheme>(selectedTheme.charAt(0).toUpperCase() + selectedTheme.slice(1)).replace(/-dark/i, \"Dark\");\n        // custom code end\n    };\n    constructor() {\n        //code\n    };\n}","polyfills.ts":"import 'zone.js';","app/app.config.ts":"import { ApplicationConfig } from '@angular/core';\n\n export const appConfig: ApplicationConfig = { providers: [], };","index.html":"<!doctype html>\n<html lang=\"en\">\n<head>\n  <meta charset=\"utf-8\">\n  <title>Window</title>\n  <base href=\"/\">\n  <meta name=\"viewport\" content=\"width=device-width, initial-scale=1\">\n  <link rel=\"icon\" type=\"image/x-icon\" href=\"favicon.ico\">\n</head>\n<body class=\"ej2-new\"> \n\n              <!-- Google Tag Manager (noscript) -->\n              <noscript><iframe src=\"https://www.googletagmanager.com/ns.html?id=GTM-W8WD8WN\" height=\"0\" width=\"0\" style=\"display:none;visibility:hidden\"></iframe></noscript>\n              <!-- End Google Tag Manager (noscript) -->\n           <div hidden id=\"sync-analytics\" data-queue=\"EJ2 - Angular - Demos\"></div>\n\n  <app-root></app-root>\n</body>\n</html>\n","app.component.html":"<style>\r\n.control-section{\r\n    margin-top: 100px;\r\n}\r\n\r</style>\n<div class=\"control-section\">\n    <div>\n        <ejs-heatmap id='container' style=\"display:block;\" [titleSettings]='titleSettings' [dataSource]='dataSource' [dataSourceSettings]='dataSourceSettings' [xAxis]='xAxis'\n            [yAxis]='yAxis' [paletteSettings]='paletteSettings' [cellSettings]='cellSettings' [legendSettings]='legendSettings' [tooltipSettings]='tooltipSettings' (tooltipRender)='tooltipRender($event)'\n            (load)='load($event)'>\n        </ejs-heatmap>\n    </div>\n    <div style=\"float: right; margin-right: 10px;\">Source:\n        <a href=\"https://en.wikipedia.org/wiki/2016_Summer_Olympics_medal_table\" target=\"_blank\">https://en.wikipedia.org/</a>\n    </div>\n</div>","app.component.css":"","dependencies.json":"{\"@syncfusion/ej2-base\":\"*\",\"@syncfusion/ej2-angular-base\":\"*\",\"@syncfusion/ej2-heatmap\":\"*\",\"tslib\":\"^2.3.0\",\"@syncfusion/ej2-angular-heatmap\":\"*\",\"@syncfusion/ej2-data\":\"*\",\"codemirror\":\"5.65.15\",\"marked\":\"0.3.19\",\"@types/codemirror\":\"0.0.56\",\"@types/marked\":\"0.3.0\",\"@angular/http\":\"*\",\"rxjs-compat\":\"*\",\"core-js\":\"2.6.9\"}"}