{"main.ts":"import { bootstrapApplication } from '@angular/platform-browser'; \n\nimport { appConfig } from './app/app.config'; \n\nimport { AppComponent } from './app.component';\n\nbootstrapApplication(AppComponent, appConfig).catch((err) => console.error(err));","angular.json":"{\n    \"$schema\": \"./node_modules/@angular/cli/lib/config/schema.json\",\n    \"version\": 1,\n    \"newProjectRoot\": \"projects\",\n    \"projects\": {\n      \"demo\": {\n        \"root\": \"\",\n        \"sourceRoot\": \"\",\n        \"projectType\": \"application\",\n        \"prefix\": \"app\",\n        \"schematics\": {},\n        \"architect\": {\n          \"build\": {\n            \"builder\": \"@angular-devkit/build-angular:browser\",\n            \"options\": {\n              \"outputPath\": \"dist/demo\",\n              \"index\": \"index.html\",\n              \"main\": \"main.ts\",\n              \"polyfills\": \"polyfills.ts\",\n              \"tsConfig\": \"tsconfig.app.json\",\n              \"assets\": [\n                \"favicon.ico\",\n                \"assets\"\n              ],\n              \"styles\": [\n                \n              ],\n              \"scripts\": []\n            },\n            \"configurations\": {\n              \"production\": {\n                \"fileReplacements\": [\n                  {\n                    \"replace\": \"src/environments/environment.ts\",\n                    \"with\": \"src/environments/environment.prod.ts\"\n                  }\n                ],\n                \"optimization\": true,\n                \"outputHashing\": \"all\",\n                \"sourceMap\": false,\n                \"extractCss\": true,\n                \"namedChunks\": false,\n                \"aot\": true,\n                \"extractLicenses\": true,\n                \"vendorChunk\": false,\n                \"buildOptimizer\": true\n              }\n            }\n          },\n          \"serve\": {\n            \"builder\": \"@angular-devkit/build-angular:dev-server\",\n            \"options\": {\n              \"browserTarget\": \"demo:build\"\n            },\n            \"configurations\": {\n              \"production\": {\n                \"browserTarget\": \"demo:build:production\"\n              }\n            }\n          },\n          \"extract-i18n\": {\n            \"builder\": \"@angular-devkit/build-angular:extract-i18n\",\n            \"options\": {\n              \"browserTarget\": \"demo:build\"\n            }\n          },\n          \"test\": {\n            \"builder\": \"@angular-devkit/build-angular:karma\",\n            \"options\": {\n              \"main\": \"src/test.ts\",\n              \"polyfills\": \"src/polyfills.ts\",\n              \"tsConfig\": \"src/tsconfig.spec.json\",\n              \"karmaConfig\": \"src/karma.conf.js\",\n              \"styles\": [\n                \"styles.css\"\n              ],\n              \"scripts\": [],\n              \"assets\": [\n                \"src/favicon.ico\",\n                \"src/assets\"\n              ]\n            }\n          },\n          \"lint\": {\n            \"builder\": \"@angular-devkit/build-angular:tslint\",\n            \"options\": {\n              \"tsConfig\": [\n                \"src/tsconfig.app.json\",\n                \"src/tsconfig.spec.json\"\n              ],\n              \"exclude\": [\n                \"**/node_modules/**\"\n              ]\n            }\n          }\n        }\n      }\n    },\n    \"defaultProject\": \"demo\"\n  }\n  \n","app.component.ts":"import { Component, ViewEncapsulation, ViewChild } from '@angular/core';\nimport { SliderComponent, SliderChangeEventArgs, SliderModule } from '@syncfusion/ej2-angular-inputs';\nimport { CheckBoxComponent, ButtonModule, CheckBoxModule } from '@syncfusion/ej2-angular-buttons';\nimport { DialogComponent, DialogModule } from '@syncfusion/ej2-angular-popups';\n\n\n\n/**\n * slider property customization\n */\n@Component({\n    selector: 'app-root',\n    templateUrl: 'app.component.html',\n    styleUrls: ['app.component.css'],\n    encapsulation: ViewEncapsulation.None,\n    standalone: true,\n    imports: [SliderModule, ButtonModule, CheckBoxModule, DialogModule,  ]\n})\n\nexport class AppComponent {\n    @ViewChild('processorSlider')\n    public processorSlider: any;\n    @ViewChild('memorySlider')\n    public memorySlider: any;\n    @ViewChild('storageSlider')\n    public storageSlider: any;\n    @ViewChild('dialog')\n    public dialogInstance: DialogComponent;\n    @ViewChild('discountCheckbox')\n    public discountCheckbox: CheckBoxComponent;\n    @ViewChild('cPanelCheckbox')\n    public cPanelCheckbox: CheckBoxComponent;\n    public buttonCss: string = 'e-info';\n    public processorValue: number = 4;\n    public processorMin: number = 1;\n    public processorMax: number = 16;\n    public memoryValue: number = 4;\n    public memoryMin: number = 1;\n    public memoryMax: number = 12;\n    public storageValue: number = 300;\n    public storageMin: number = 10;\n    public storageMax: number = 500;\n    public storageStep: number = 10;\n    public target: string = '#pricing-slider';\n    public width: string = '360px';\n    public animationSettings: any = { effect: 'None' };\n    public alertContent: string = '<div id = \"dialog-content\"><div id = \"dialog-header\">Cloud Price Details</div>' +\n        '<div id=\"processorDialog\"><span id=\"processorPriceName\">Processor Price</span><span id=\"processorPrice\"></span></div>' +\n        '<div id=\"MemoryDialog\"><span id=\"memoryPriceName\">Memory Price</span><span id=\"memoryPrice\"></span></div>' +\n        '<div id=\"StorgeDialog\"><span id=\"storgePriceName\">Storge Price</span><span id=\"storgePrice\"></span></div>' +\n        '<div id=\"CloudDialog\"><span id=\"cloudPriceName\">Estimated Price</span><span id=\"cloudPrice\"></span></div></div>';\n    public alertDlgButtons: any = [{\n        click: this.alertDlgBtnClick.bind(this), buttonModel: { content: 'Close', isPrimary: true }\n    }];\n    public proceessorElem: HTMLElement;\n    public memoryElem: HTMLElement;\n    public storageElem: HTMLElement;\n    public elemValue: HTMLElement;\n    public finalValue: number;\n    public discountValue: number;\n    ngOnInit() {\n        //change the slider value based on workload\n        document.getElementById('xSmallBtn').onclick = (e: Event) => {\n            this.sliderPriceValue(1, 1, 10);\n        };\n        document.getElementById('smallBtn').onclick = (e: Event) => {\n            this.sliderPriceValue(1, 2, 10);\n        };\n        document.getElementById('mediumBtn').onclick = (e: Event) => {\n            this.sliderPriceValue(4, 4, 300);\n        };\n        document.getElementById('largeBtn').onclick = (e: Event) => {\n            this.sliderPriceValue(12, 6, 100);\n        };\n        document.getElementById('xLargeBtn').onclick = (e: Event) => {\n            this.sliderPriceValue(8, 12, 300);\n        };\n        document.getElementById('btn').onclick = (e: Event) => {\n            let processorPrice: HTMLElement = document.getElementById('processorPrice');\n            this.onChange(processorPrice, <number>this.processorSlider.value, 'CORE');\n            let memoryPrice: HTMLElement = document.getElementById('memoryPrice');\n            this.onChange(memoryPrice, <number>this.memorySlider.value, 'GB');\n            let storgePrice: HTMLElement = document.getElementById('storgePrice');\n            this.onChange(storgePrice, <number>this.storageSlider.value, 'GB');\n            let cloudPrice: HTMLElement = document.getElementById('cloudPrice');\n            cloudPrice.innerText = '$' + this.finalValue;\n            this.sliderValueChange();\n            this.dialogInstance.refreshPosition();\n            this.dialogInstance.show();\n        };\n    }\n\n    sliderPriceValue(processor: number, memory: number, storage: number): void {\n        this.processorSlider.value = processor;\n        this.processorSlider.dataBind();\n        this.memorySlider.value = memory;\n        this.memorySlider.dataBind();\n        this.storageSlider.value = storage;\n        this.storageSlider.dataBind();\n    }\n    //Sets processor value\n    onCreateProcessor(args: any): void {\n        document.getElementById('processor').innerHTML = this.processorSlider.value + '  ' + 'CORE';\n    }\n    //Sets memory value\n    onCreateMemory(args: any): void {\n        document.getElementById('memory').innerHTML = this.memorySlider.value + '  ' + 'GB';\n    }\n    //Sets storage value\n    onCreateStorage(args: any): void {\n        document.getElementById('storage').innerHTML = this.storageSlider.value + '  ' + 'GB';\n        this.sliderValueChange();\n    }\n\n    //Processor Slider value change method\n    onChangeProcessor(args: SliderChangeEventArgs): void {\n        this.onChange(document.getElementById('processor'), <number>args.value, 'CORE');\n    }\n\n    //Memory Slider value change method\n    onChangeMemory(args: SliderChangeEventArgs): void {\n        this.onChange(document.getElementById('memory'), <number>args.value, 'GB');\n    }\n\n    //Storage Slider value change method\n    onChangeStorage(args: SliderChangeEventArgs): void {\n        this.onChange(document.getElementById('storage'), <number>args.value, 'GB');\n    }\n    //common method for Slider value change\n    onChange(elem: HTMLElement, value: number, notation: string): void {\n        elem.innerText = value + '  ' + notation;\n        this.sliderValueChange();\n    }\n    sliderValueChange(): void {\n        this.elemValue = document.getElementById('value');\n        let porcessorValue: number = <number>this.processorSlider.value;\n        let memoryValue: number = <number>this.memorySlider.value;\n        let storageValue: number = <number>this.storageSlider.value;\n        //formula to calculate cloud price based on slider value\n        this.finalValue = Number(((((porcessorValue * memoryValue) * 1000) + ((porcessorValue * memoryValue) * storageValue)\n            + ((porcessorValue * memoryValue) * 100)) / 12).toFixed(2));\n        if (this.cPanelCheckbox && this.cPanelCheckbox.checked) {\n            this.finalValue = Number((this.finalValue - 10).toFixed(2));\n        }\n        if (this.discountCheckbox && this.discountCheckbox.checked) {\n            this.finalValue = Number((this.finalValue - ((this.finalValue * 25) / 100)).toFixed(2));\n        }\n        this.elemValue.innerText = this.finalValue.toString();\n    }\n\n    alertDlgBtnClick(): void {\n        this.dialogInstance.hide();\n    }\n}\n","polyfills.ts":"import 'zone.js';","app/app.config.ts":"import { ApplicationConfig } from '@angular/core';\n\n export const appConfig: ApplicationConfig = { providers: [], };","index.html":"<!doctype html>\n        <html lang=\"en\">\n          <head>\n            <meta charset=\"utf-8\">\n            <title>Window</title>\n            <base href=\"/\">\n            <meta name=\"viewport\" content=\"width=device-width, initial-scale=1\">\n            <link rel=\"icon\" type=\"image/x-icon\" href=\"favicon.ico\">\n            <link href=\"https://maxcdn.bootstrapcdn.com/bootstrap/3.3.7/css/bootstrap.min.css\" rel=\"stylesheet\" >\n          </head>\n          <body class=\"ej2-new\"> \n\n              <!-- Google Tag Manager (noscript) -->\n              <noscript><iframe src=\"https://www.googletagmanager.com/ns.html?id=GTM-W8WD8WN\" height=\"0\" width=\"0\" style=\"display:none;visibility:hidden\"></iframe></noscript>\n              <!-- End Google Tag Manager (noscript) -->\n           <div hidden id=\"sync-analytics\" data-queue=\"EJ2 - Angular - Demos\"></div>\n            <app-root></app-root>\n          </body>\n        </html>","app.component.html":"<style>\r\n.control-section{\r\n    margin-top: 100px;\r\n}\r\n\r</style>\n<div class=\"col-lg-10 control-section azure\">\n    <div class=\"cloud-content-wrapper\">\n        <div id=\"pricing-slider\" class=\"pricing-slider\">\n            <div class=\"row\">\n                <div id=\"cloud-left-pane\" class=\"col-lg-8 col-md-8 col-sm-8\">\n                    <div class=\"cloud-slider\">\n                        <div id=\"processor\"></div>\n                        <span class=\"label-text\"> Processor </span>\n                        <!-- processor Slider element -->\n                        <ejs-slider id='processor-slider' #processorSlider [value]='processorValue' [min]=\"processorMin\" [max]=\"processorMax\" (change)='onChangeProcessor($event)'\n                            (created)='onCreateProcessor($event)'></ejs-slider>\n                        <div class=\"sub-heading\"> Each core included minimum 2.26 GHz power </div>\n                    </div>\n                    <div class=\"cloud-slider cloud-left-slider\">\n                        <div id=\"memory\"></div>\n                        <span class=\"label-text\"> Memory </span>\n                        <!-- memory Slider element -->\n                        <ejs-slider id='memory-slider' #memorySlider [value]='memoryValue' [min]=\"memoryMin\" [max]=\"memoryMax\" (change)='onChangeMemory($event)'\n                            (created)='onCreateMemory($event)'></ejs-slider>\n                        <div class=\"sub-heading\"> Equal to burstable memory included </div>\n                    </div>\n                    <div class=\"cloud-slider cloud-left-slider\">\n                        <div id=\"storage\"></div>\n                        <span class=\"label-text\"> Storage </span>\n                        <!-- storage Slider element -->\n                        <ejs-slider id='storage-slider' #storageSlider [value]='storageValue' [min]='storageMin' [max]='storageMax' (change)='onChangeStorage($event)'\n                            (created)='onCreateStorage($event)'></ejs-slider>\n                        <div class=\"sub-heading\"> 1000 GB bandwidth per month, at 100 Mbit/s uplink port </div>\n                    </div>\n                </div>\n                <div id=\"cloud-right-pane\" class=\"col-lg-4 col-md-4 col-sm-4\">\n                    <div class=\"cloud-right-content\">\n                        <div class=\"label-text\"> Size Range </div>\n                        <div class=\"btn-size\">\n                            <!-- Button element -->\n                            <button id=\"xSmallBtn\" ejs-button [cssClass] = 'buttonCss' [isPrimary]=\"true\">XS</button>\n                            <button ejs-button id=\"smallBtn\" [cssClass] = 'buttonCss' [isPrimary]=\"true\">S</button>\n                            <button ejs-button id=\"mediumBtn\" [cssClass] = 'buttonCss' [isPrimary]=\"true\">M</button>\n\n                            <button ejs-button id=\"largeBtn\" [cssClass] = 'buttonCss' [isPrimary]=\"true\">L</button>\n                            <button ejs-button id=\"xLargeBtn\" [cssClass] = 'buttonCss' [isPrimary]=\"true\">XL</button>\n                        </div>\n                        <div class=\"label-text right-text\"> Estimated Price </div>\n                        <div id=\"cloud-slider-text\">\n                            <span id=dollar>$ </span>\n                            <span id=\"value\"></span>\n                            <span class=\"suffix\">/month</span>\n                        </div>\n                        <div class=\"discount\">\n                            <div class=\"cloud-slider-right\">\n                                <!-- cPanel Check Box element -->\n                                <ejs-checkbox id=\"cPanel\" #cPanelCheckbox (change)='sliderValueChange()' label=\"Not required cPanel included\" [checked]=\"false\" ></ejs-checkbox>\n\n                            </div>\n                            <div class=\"cloud-slider-right discount-pay\">\n                                <!-- discount Check Box element -->\n                                <ejs-checkbox id=\"discount\" #discountCheckbox (change)='sliderValueChange()' label='12 Months <span class = \"offer\" > Save 25%.</span> Pay Monthly'\n                                    [checked]=\"false\"></ejs-checkbox>\n                            </div>\n                        </div>\n                        <!-- Button element -->\n                        <div class=\"slider-button\">\n                            <button ejs-button id=\"btn\" class=\"dlgbtn\" [isPrimary]=\"true\">Signup Now</button>\n\n                        </div>\n                        <div id=\"dialogWrapper\" class=\"cloud-content-wrapper\">\n                            <!-- Initialize alert Dialog -->\n                            <ejs-dialog id=\"alertDialog\" #dialog [buttons]='alertDlgButtons' [animationSettings]='animationSettings' [content]='alertContent'\n                                [width]='width' [visible]='false' [closeOnEscape]='false' [showCloseIcon]='false' [target]='target'>\n                            </ejs-dialog>\n\n                        </div>\n                    </div>\n                </div>\n            </div>\n        </div>\n    </div>\n</div>\n\n","app.component.css":"html,\nbody {\n    height: 100%;\n    width: 100%;\n    margin: 0px;\n}\n\n#pricing-slider #cloud-right-pane .btn-size {\n    padding-top: 16px;\n    padding-bottom: 30px;\n    border-bottom: 1px solid lightgrey;\n}\n\n#pricing-slider .e-slider-container.e-horizontal {\n    height: 56px;\n}\n\n#pricing-slider .row {\n    border: 1px solid #CCCCCC;\n    box-shadow: 0px 0px 4px;\n    opacity: 100;\n\n    border-radius: 4px;\n}\n\n.discount .e-label,\n.discount .e-label {\n    white-space: initial;\n}\n\n#pricing-slider .sub-heading {\n    margin-top: -8px;\n    font-size: 13px;\n    color: #808080;\n}\n\n#pricing-slider .label-text.right-text {\n    padding-top: 16px;\n    padding-bottom: 20px;\n}\n\n#pricing-slider .label-text {\n    color: #000000;\n    font-size: 14px;\n    font-weight: 500;\n}\n\nspan.e-label .offer {\n    color: #4A90E2;\n}\n\n.cloud-slider {\n    display: block;\n    position: relative;\n}\n\n\n#processor {\n    background-color: #A06AFF;\n}\n\n#memory {\n    background-color: #7ED321;\n}\n\n#storage {\n    background-color: #4A90E2;\n}\n\n#memory,\n#storage,\n#processor {\n    font-size: 14px;\n    height: 24px;\n    width: 70px;\n    text-align: center;\n    line-height: 24px;\n    float: right;\n    color: #FFFFFF;\n    font-weight: 500;\n    border-radius: 18px;\n}\n\n#cloud-slider-text #value {\n    color: #000000;\n    font-size: 28px;\n    font-weight: bold;\n}\n\n#suffix {\n    color: #000000;\n    font-size: 16px;\n    font-weight: 500;\n}\n\n.text {\n    font-size: 13px;\n    padding-top: 26px;\n    width: 190px;\n}\n\n#cloud-right-pane {\n    background-color: #FFFFFF;\n    border-left: 1px solid #CCCCCC;\n    padding: 20px;\n    height: 443px;\n}\n\n.pricing-slider {\n    margin-top: 40px;\n    min-height: 20px;\n    margin-bottom: 20px;\n}\n\n.cloud-slider-right {\n    color: #000000;\n    font-size: 14px;\n}\n\n.cloud-slider-right.discount-pay {\n    padding-top: 20px;\n}\n\n#cloud-left-pane {\n    height: 443px;\n    padding: 40px;\n    background-color: #FAFAFA;\n}\n\n.discount {\n    padding-top: 20px;\n    padding-bottom: 35px;\n}\n\n@media (max-width: 1010px) {\n    #cloud-right-pane {\n        border-top: 1px solid #d5d7d8 !important;\n        border-left: none !important;\n        border-width: 1px 0 0!important;\n        padding-top: 15px !important;\n        padding-left: 0!important;\n    }\n    .cloud-right-content {\n        padding-left: 24px !important;\n    }\n    #cloud-left-pane {\n        width: 100%;\n    }\n    #cloud-right-pane {\n        width: 100%;\n    }\n}\n\n#cloud-slider-text {\n    padding-bottom: 20px;\n    border-bottom: 1px solid lightgrey;\n}\n\n#dollar {\n    color: #000000;\n    font-size: 14px;\n    font-weight: 500;\n    position: relative;\n    top: -7px;\n}\n\n\n#btn {\n    text-transform: uppercase;\n    width: -webkit-fill-available;\n}\n\n.cloud-left-slider {\n    margin-top: 40px;\n}\n\n.azure.control-section {\n    padding-top: 0px;\n    margin-left: 75px;\n    overflow: hidden;\n}\n\n@media screen and (max-width: 1199px) {\n    .azure.control-section {\n        margin-left: 0px;\n    }\n}\n\n.cloud-right-content .e-btn.e-info {\n    padding: 0px;\n    width: 30px;\n    height: 30px;\n    line-height: inherit;\n    margin: 2px;\n}\n\n.highcontrast .pricing-slider,\n.highcontrast #pricing-slider .label-text,\n.highcontrast #pricing-slider .sub-heading,\n.material-dark .pricing-slider,\n.material-dark #pricing-slider .label-text,\n.material-dark #pricing-slider .sub-heading,\n.material3-dark .pricing-slider,\n.material3-dark #pricing-slider .label-text,\n.material3-dark #pricing-slider .sub-heading,\n.fabric-dark .pricing-slider,\n.fabric-dark #pricing-slider .label-text,\n.fabric-dark #pricing-slider .sub-heading,\n.fluent-dark .pricing-slider,\n.fluent-dark #pricing-slider .label-text,\n.fluent-dark #pricing-slider .sub-heading,\n.fluent2-dark .pricing-slider,\n.fluent2-dark #pricing-slider .label-text,\n.fluent2-dark #pricing-slider .sub-heading,\n.fluent2-highcontrast .pricing-slider,\n.fluent2-highcontrast #pricing-slider .label-text,\n.fluent2-highcontrast #pricing-slider .sub-heading,\n.tailwind-dark .pricing-slider,\n.tailwind-dark #pricing-slider .label-text,\n.tailwind-dark #pricing-slider .sub-heading,\n.bootstrap5-dark .pricing-slider,\n.bootstrap5-dark #pricing-slider .label-text,\n.bootstrap5-dark #pricing-slider .sub-heading,\n.bootstrap-dark .pricing-slider,\n.bootstrap-dark #pricing-slider .label-text,\n.bootstrap-dark #pricing-slider .sub-heading {\n    color: white;\n}\n\n.fabric .cloud-right-content .e-btn.e-info,\n.highcontrast .e-btn.e-info {\n    line-height: 2px;\n}\n\n.highcontrast #dollar,\n.highcontrast #cloud-slider-text #value,\n.highcontrast #dialog-header,\n.highcontrast #StorgeDialog,\n.highcontrast #CloudDialog,\n.highcontrast #processorDialog,\n.material-dark #dollar,\n.material-dark #cloud-slider-text #value,\n.material-dark #dialog-header,\n.material-dark #StorgeDialog,\n.material-dark #CloudDialog,\n.material-dark #processorDialog,\n.material3-dark #dollar,\n.material3-dark #cloud-slider-text #value,\n.material3-dark #dialog-header,\n.material3-dark #StorgeDialog,\n.material3-dark #CloudDialog,\n.material3-dark #processorDialog,\n.fabric-dark #dollar,\n.fabric-dark #cloud-slider-text #value,\n.fabric-dark #dialog-header,\n.fabric-dark #StorgeDialog,\n.fabric-dark #CloudDialog,\n.fabric-dark #processorDialog,\n.fluent-dark #dollar,\n.fluent-dark #cloud-slider-text #value,\n.fluent-dark #dialog-header,\n.fluent-dark #StorgeDialog,\n.fluent-dark #CloudDialog,\n.fluent-dark #processorDialog,\n.fluent2-dark #dollar,\n.fluent2-dark #cloud-slider-text #value,\n.fluent2-dark #dialog-header,\n.fluent2-dark #StorgeDialog,\n.fluent2-dark #CloudDialog,\n.fluent2-dark #processorDialog,\n.fluent2-highcontrast #dollar,\n.fluent2-highcontrast #cloud-slider-text #value,\n.fluent2-highcontrast #dialog-header,\n.fluent2-highcontrast #StorgeDialog,\n.fluent2-highcontrast #CloudDialog,\n.fluent2-highcontrast #processorDialog,\n.bootstrap-dark #dollar,\n.bootstrap-dark #cloud-slider-text #value,\n.bootstrap-dark #dialog-header,\n.bootstrap-dark #StorgeDialog,\n.bootstrap-dark #CloudDialog,\n.bootstrap-dark #processorDialog,\n.bootstrap5-dark #dollar,\n.bootstrap5-dark #cloud-slider-text #value,\n.bootstrap5-dark #dialog-header,\n.bootstrap5-dark #StorgeDialog,\n.bootstrap5-dark #CloudDialog,\n.bootstrap5-dark #processorDialog,\n.tailwind-dark #dollar,\n.tailwind-dark #cloud-slider-text #value,\n.tailwind-dark #dialog-header,\n.tailwind-dark #StorgeDialog,\n.tailwind-dark #CloudDialog,\n.tailwind-dark #processorDialog,\n.bootstrap5\\.3-dark #dialog-header,\n.bootstrap5\\.3-dark #StorgeDialog,\n.bootstrap5\\.3-dark #CloudDialog,\n.bootstrap5\\.3-dark #processorDialog {\n    color: white;\n}\n\n.highcontrast #pricing-slider .row,\n.tailwind-dark #pricing-slider .row,\n.bootstrap-dark #pricing-slider .row,\n.bootstrap5-dark #pricing-slider .row,\n.fabric-dark #pricing-slider .row,\n.fluent-dark #pricing-slider .row,\n.fluent2-dark #pricing-slider .row,\n.fluent2-highcontrast #pricing-slider .row,\n.material-dark #pricing-slider .row,\n.material3-dark #pricing-slider .row {\n    border: 1px solid #969696;\n}\n\n.highcontrast #cloud-right-pane,\n.tailwind-dark #cloud-right-pane,\n.bootstrap-dark #cloud-right-pane,\n.bootstrap5-dark #cloud-right-pane,\n.fabric-dark #cloud-right-pane,\n.fluent-dark #cloud-right-pane,\n.fluent2-dark #cloud-right-pane,\n.fluent2-highcontrast #cloud-right-pane,\n.material-dark #cloud-right-pane,\n.material3-dark #cloud-right-pane\n{\n    border-left: 1px solid #969696;\n}\n\n.highcontrast #cloud-slider-text,\n.highcontrast #pricing-slider #cloud-right-pane .btn-size,\n.material-dark #cloud-slider-text,\n.material-dark #pricing-slider #cloud-right-pane .btn-size,\n.material3-dark #cloud-slider-text,\n.material3-dark #pricing-slider #cloud-right-pane .btn-size,\n.fabric-dark #cloud-slider-text,\n.fabric-dark #pricing-slider #cloud-right-pane .btn-size,\n.fluent-dark #cloud-slider-text,\n.fluent-dark #pricing-slider #cloud-right-pane .btn-size,\n.fluent2-dark #cloud-slider-text,\n.fluent2-dark #pricing-slider #cloud-right-pane .btn-size,\n.fluent2-highcontrast #cloud-slider-text,\n.fluent2-highcontrast #pricing-slider #cloud-right-pane .btn-size,\n.bootstrap-dark #cloud-slider-text,\n.bootstrap-dark #pricing-slider #cloud-right-pane .btn-size,\n.bootstrap5-dark #cloud-slider-text,\n.bootstrap5-dark #pricing-slider #cloud-right-pane .btn-size,\n.tailwind-dark #cloud-slider-text,\n.tailwind-dark #pricing-slider #cloud-right-pane .btn-size {\n    border-bottom: 1px solid #969696;\n}\n\n.highcontrast #processor,\n.tailwind-dark #processor,\n.bootstrap-dark #processor,\n.bootstrap5-dark #processor,\n.fabric-dark #processor,\n.fluent-dark #processor,\n.fluent2-dark #processor,\n.fluent2-highcontrast #processor,\n.material-dark #processor,\n.material3-dark #processor {\n    background-color: #AE80FF;\n}\n\n.highcontrast #memory,\n.tailwind-dark #memory,\n.bootstrap-dark #memory,\n.bootstrap5-dark #memory,\n.fabric-dark #memory,\n.fluent-dark #memory,\n.fluent2-dark #memory,\n.fluent2-highcontrast #memory,\n.material-dark #memory,\n.material3-dark #memory {\n    background-color: #7ED321;\n}\n\n.highcontrast #storage,\n.tailwind-dark #storage,\n.bootstrap-dark #storage,\n.bootstrap5-dark #storage,\n.fabric-dark #storage,\n.fluent-dark #storage,\n.fluent2-dark #storage,\n.fluent2-highcontrast #storage,\n.material-dark #storage,\n.material3-dark #storage {\n    background-color: #61A4EF;\n}\n\n.highcontrast #cloud-left-pane,\n.tailwind-dark #cloud-left-pane,\n.bootstrap-dark #cloud-left-pane,\n.bootstrap5-dark #cloud-left-pane,\n.fabric-dark #cloud-left-pane,\n.fluent-dark #cloud-left-pane,\n.fluent2-dark #cloud-left-pane,\n.fluent2-highcontrast #cloud-left-pane,\n.material-dark #cloud-left-pane,\n.material3-dark #cloud-left-pane {\n    background-color: #1a1a1a;\n}\n\n.highcontrast #cloud-right-pane,\n.tailwind-dark #cloud-right-pane,\n.bootstrap-dark #cloud-right-pane,\n.bootstrap5-dark #cloud-right-pane,\n.fabric-dark #cloud-right-pane,\n.fluent-dark #cloud-right-pane,\n.fluent2-dark #cloud-right-pane,\n.fluent2-highcontrast #cloud-right-pane,\n.material-dark #cloud-right-pane,\n.material3-dark #cloud-right-pane {\n    background-color: #000;\n}\n\n.highcontrast #processorPriceName,\n.highcontrast #memoryPriceName,\n.highcontrast #storgePriceName,\n.highcontrast #cloudPriceName,\n.tailwind-dark #processorPriceName,\n.tailwind-dark #memoryPriceName,\n.tailwind-dark #storgePriceName,\n.tailwind-dark #cloudPriceName,\n.bootstrap-dark #processorPriceName,\n.bootstrap-dark #memoryPriceName,\n.bootstrap-dark #storgePriceName,\n.bootstrap-dark #cloudPriceName,\n.bootstrap5-dark #processorPriceName,\n.bootstrap5-dark #memoryPriceName,\n.bootstrap5-dark #storgePriceName,\n.bootstrap5-dark #cloudPriceName,\n.fabric-dark #processorPriceName,\n.fabric-dark #memoryPriceName,\n.fabric-dark #storgePriceName,\n.fabric-dark #cloudPriceName,\n.fluent-dark #processorPriceName,\n.fluent-dark #memoryPriceName,\n.fluent-dark #storgePriceName,\n.fluent-dark #cloudPriceName,\n.fluent2-dark #processorPriceName,\n.fluent2-dark #memoryPriceName,\n.fluent2-dark #storgePriceName,\n.fluent2-dark #cloudPriceName,\n.fluent2-highcontrast #processorPriceName,\n.fluent2-highcontrast #memoryPriceName,\n.fluent2-highcontrast #storgePriceName,\n.fluent2-highcontrast #cloudPriceName,\n.material-dark #processorPriceName,\n.material-dark #memoryPriceName,\n.material-dark #storgePriceName,\n.material-dark #cloudPriceName,\n.material3-dark #processorPriceName,\n.material3-dark #memoryPriceName,\n.material3-dark #storgePriceName,\n.material3-dark #cloudPriceName,\n.bootstrap5\\.3-dark #processorPriceName,\n.bootstrap5\\.3-dark #memoryPriceName,\n.bootstrap5\\.3-dark #storgePriceName,\n.bootstrap5\\.3-dark #cloudPriceName {\n    color: white;\n    opacity: 1;\n}\n\n.bootstrap5\\.3-dark .discount .e-label, .bootstrap5\\.3-dark #cloud-slider-text .suffix,\n.tailwind3-dark .discount .e-label, .tailwind3-dark #cloud-slider-text .suffix {\n    color: black;\n}\n\n#dialog-header {\n    color: #000000;\n    opacity: .87;\n    font-weight: 600;\n    font-size: 20px;\n}\n\n#CloudDialog {\n    color: #000000;\n    padding-top: 14px;\n    padding-bottom: 24px;\n    border-top: 1px solid #CCCCCC;\n}\n\n#processorPrice,\n#memoryPrice,\n#storgePrice {\n    opacity: 0.9;\n    font-weight: 600;\n    font-size: 16px;\n    float: right;\n}\n\n#alertDialog .e-footer-content {\n    padding-top: 0;\n}\n\n#processorPriceName,\n#memoryPriceName,\n#storgePriceName,\n#cloudPriceName {\n    opacity: 0.9;\n    color: #000000;\n    font-size: 16px;\n}\n\n#cloudPrice {\n    opacity: 0.9;\n    font-weight: 600;\n    font-size: 26px;\n    float: right;\n}\n\n#processorDialog {\n    color: #000000;\n    padding-top: 12px;\n    padding-bottom: 12px;\n}\n\n#StorgeDialog {\n    color: #000000;\n    padding-top: 12px;\n    padding-bottom: 16px;\n}\n\n.bootstrap4 #pricing-slider .row {\n    box-shadow: none;\n}\n","dependencies.json":"{\"@syncfusion/ej2-base\":\"*\",\"@syncfusion/ej2-angular-base\":\"*\",\"@syncfusion/ej2-inputs\":\"*\",\"tslib\":\"^2.3.0\",\"@syncfusion/ej2-angular-inputs\":\"*\",\"@syncfusion/ej2-buttons\":\"*\",\"@syncfusion/ej2-angular-buttons\":\"*\",\"@syncfusion/ej2-popups\":\"*\",\"@syncfusion/ej2-angular-popups\":\"*\",\"@syncfusion/ej2-dropdowns\":\"*\",\"@syncfusion/ej2-angular-dropdowns\":\"*\",\"@syncfusion/ej2-data\":\"*\",\"codemirror\":\"5.65.15\",\"marked\":\"0.3.19\",\"@types/codemirror\":\"0.0.56\",\"@types/marked\":\"0.3.0\",\"@angular/http\":\"*\",\"rxjs-compat\":\"*\",\"core-js\":\"2.6.9\",\"fuse.js\":\"^7.0.0\"}"}